setup.py
kaichu/__init__.py
kaichu/interface.py
kaichu/jira_lib.py
kaichu/models.py
kaichu.egg-info/PKG-INFO
kaichu.egg-info/SOURCES.txt
kaichu.egg-info/dependency_links.txt
kaichu.egg-info/entry_points.txt
kaichu.egg-info/requires.txt
kaichu.egg-info/top_level.txt