Metadata-Version: 1.1
Name: kaichu
Version: 0.0.1
Summary: A Sneeze plugin for JIRA integration
Home-page: https://github.com/NYTimes/kaichu
Author: Silas Ray
Author-email: silas.ray@nytimes.com
License: Apache2.0
Platform: UNKNOWN
Classifier: Development Status :: 4 - Beta
Classifier: Intended Audience :: Information Technology
Classifier: Topic :: Software Development :: Quality Assurance
Classifier: Topic :: Software Development :: Testing
